nanoloop/__init__.py
nanoloop/arg_parser.py
nanoloop/bam_to_json.py
nanoloop/bam_to_tsv.py
nanoloop/cli.py
nanoloop/cluster_hotspot.py
nanoloop/constants.py
nanoloop/filter_json.py
nanoloop/json_to_hotspot.py
nanoloop/stat_hotspot.py
nanoloop/tsv_to_bed.py
nanoloop/tsv_to_peak.py
nanoloop/tsv_to_plot.py
nanoloop/utils.py
nanoloop-0.3.2.dist-info/METADATA
nanoloop-0.3.2.dist-info/WHEEL
nanoloop-0.3.2.dist-info/entry_points.txt
nanoloop-0.3.2.dist-info/RECORD
