Metadata-Version: 2.3
Name: nanoloop
Version: 0.3.2
Summary: Utility tool for detecting R-loops with Nanopore data
Author: hukai916
Author-email: hukai916@gmail.com
Requires-Python: >=3.10
Classifier: Programming Language :: Python :: 3
Classifier: Programming Language :: Python :: 3.10
Classifier: Programming Language :: Python :: 3.11
Classifier: Programming Language :: Python :: 3.12
Classifier: Programming Language :: Python :: 3.13
Requires-Dist: argparse (>=1.4.0,<2.0.0)
Requires-Dist: dask (>=2025.4.1,<2026.0.0)
Requires-Dist: fastcluster (>=1.3.0,<2.0.0)
Requires-Dist: matplotlib (>=3.10.1,<4.0.0)
Requires-Dist: pandas (>=2.2.3,<3.0.0)
Requires-Dist: pyarrow (>=20.0.0,<21.0.0)
Requires-Dist: pysam (>=0.23.0,<0.24.0)
Requires-Dist: scipy (>=1.15.3,<2.0.0)
Requires-Dist: seaborn (>=0.13.2,<0.14.0)
Requires-Dist: statistics (>=1.0.3.5,<2.0.0.0)
